abSENSE/__init__.py
abSENSE/__main__.py
abSENSE/analyzer.py
abSENSE/constants.py
abSENSE/exceptions.py
abSENSE/parameters.py
abSENSE/plotting.py
abSENSE/py.typed
abSENSE/pyodide_utilities.py
abSENSE/recorder.py
abSENSE/results.py
abSENSE/utilities.py
abSENSE-0.1.6.dist-info/entry_points.txt
abSENSE-0.1.6.dist-info/WHEEL
abSENSE-0.1.6.dist-info/METADATA
abSENSE-0.1.6.dist-info/license_files/LICENSE
abSENSE-0.1.6.dist-info/RECORD
