Metadata-Version: 2.1
Name: abSENSE
Version: 0.1.6
Summary: Perform homolog detectability
Author-email: Troy Comi <tcomi@princeton.edu>
Maintainer-email: Troy Comi <tcomi@princeton.edu>
Requires-Python: >=3.7
Classifier: Development Status :: 1 - Planning
Classifier: Intended Audience :: Developers
Classifier: Intended Audience :: Science/Research
Classifier: License :: OSI Approved :: BSD License
Classifier: Operating System :: OS Independent
Classifier: Programming Language :: Python
Classifier: Programming Language :: Python :: 3
Classifier: Programming Language :: Python :: 3.10
Classifier: Programming Language :: Python :: 3.7
Classifier: Programming Language :: Python :: 3.8
Classifier: Programming Language :: Python :: 3.9
Classifier: Topic :: Scientific/Engineering
Requires-Dist: click>=8.1.2
Requires-Dist: matplotlib>=3.5.1
Requires-Dist: numpy>=1.21.1
Requires-Dist: pandas>=1.1.5
Requires-Dist: scipy>=1.6.1
Requires-Dist: typing_extensions >=3.7; python_version<'3.8'
Provides-Extra: dev
Requires-Dist: pytest>=6; extra == "dev"
Requires-Dist: pytest-mock>=3.7.0; extra == "dev"
Provides-Extra: docs
Requires-Dist: Sphinx>=4.0; extra == "docs"
Requires-Dist: myst_parser>=0.13; extra == "docs"
Requires-Dist: sphinx-book-theme>=0.1.0; extra == "docs"
Requires-Dist: sphinx_copybutton; extra == "docs"
Provides-Extra: test
Requires-Dist: pytest>=6; extra == "test"
Requires-Dist: pytest-mock>=3.7.0; extra == "test"
Project-URL: homepage, https://github.com/PrincetonUniversity/abSENSE
